rspet_server-0.4.0-py2.7-nspkg.pth
rspet/server/__init__.py
rspet/server/api.py
rspet/server/base.py
rspet/server/config.json
rspet/server/tab.py
rspet/server/Plugins/__init__.py
rspet/server/Plugins/essentials.py
rspet/server/Plugins/files.py
rspet/server/Plugins/geolocation.py
rspet/server/Plugins/mount.py
rspet/server/Plugins/template.py
rspet/server/Plugins/udp.py
rspet/server/Plugins/Client/geolocation.client
rspet_server-0.4.0.dist-info/DESCRIPTION.rst
rspet_server-0.4.0.dist-info/METADATA
rspet_server-0.4.0.dist-info/RECORD
rspet_server-0.4.0.dist-info/WHEEL
rspet_server-0.4.0.dist-info/entry_points.txt
rspet_server-0.4.0.dist-info/metadata.json
rspet_server-0.4.0.dist-info/namespace_packages.txt
rspet_server-0.4.0.dist-info/top_level.txt
