Metadata-Version: 2.0
Name: rspet-server
Version: 0.4.0
Summary: Server module of the RSPET Post-Exploitation Toolset.
Home-page: https://github.com/panagiks/RSPET
Author: panagiks
Author-email: UNKNOWN
License: MIT
Keywords: rspet post exploitation security reverse shell
Platform: UNKNOWN
Classifier: Development Status :: 4 - Beta
Classifier: License :: OSI Approved :: MIT License
Classifier: Programming Language :: Python :: 2.7
Classifier: Topic :: Security
Classifier: Operating System :: POSIX
Classifier: Operating System :: Unix
Classifier: Operating System :: Microsoft :: Windows
Classifier: Operating System :: MacOS
Requires-Dist: asn1crypto
Requires-Dist: certbuilder
Requires-Dist: oscrypto
Provides-Extra: rest
Requires-Dist: Flask; extra == 'rest'
Requires-Dist: flask-cors; extra == 'rest'
